setup.py
./__init__.py
./api.py
yubicoclient.egg-info/PKG-INFO
yubicoclient.egg-info/SOURCES.txt
yubicoclient.egg-info/dependency_links.txt
yubicoclient.egg-info/top_level.txt