Metadata-Version: 1.0
Name: yubicoclient
Version: 0.2.0
Summary: Python yubico client
Home-page: http://www.openlabs.co.in/
Author: Sharoon Thomas, Openlabs Technologies & Consulting (P) Limited
Author-email: UNKNOWN
License: BSD
Platform: any
Classifier: Development Status :: 4 - Beta
Classifier: Intended Audience :: Developers
Classifier: License :: OSI Approved :: BSD License
Classifier: Operating System :: OS Independent
Classifier: Programming Language :: Python
Classifier: Topic :: Software Development :: Libraries :: Python Modules
